LICENSE
MANIFEST.in
README.md
package.json
setup.py
dash_wtgviewer/DashWtgviewer.py
dash_wtgviewer/__init__.py
dash_wtgviewer/_imports_.py
dash_wtgviewer/dash_wtgviewer.min.js
dash_wtgviewer/dash_wtgviewer.min.js.map
dash_wtgviewer/metadata.json
dash_wtgviewer/package-info.json
dash_wtgviewer.egg-info/PKG-INFO
dash_wtgviewer.egg-info/SOURCES.txt
dash_wtgviewer.egg-info/dependency_links.txt
dash_wtgviewer.egg-info/top_level.txt
dash_wtgviewer/model/__init__.py
dash_wtgviewer/model/base.py
dash_wtgviewer/model/blade.py
dash_wtgviewer/model/foundation.py
dash_wtgviewer/model/hub.py
dash_wtgviewer/model/model.py
dash_wtgviewer/model/nacelle.py
dash_wtgviewer/model/rotor.py
dash_wtgviewer/model/tower.py
dash_wtgviewer/model/fea/__init__.py
dash_wtgviewer/model/fea/base.py
dash_wtgviewer/model/fea/elements.py
dash_wtgviewer/model/fea/nodes.py
dash_wtgviewer/model/geometry/__init__.py
dash_wtgviewer/model/geometry/vectors.py
dash_wtgviewer/model/results/__init__.py
dash_wtgviewer/model/results/base.py
dash_wtgviewer/model/results/element.py
dash_wtgviewer/model/results/results.py
dash_wtgviewer/model/results/sp.py