Metadata-Version: 2.1
Name: dash-wtgviewer
Version: 0.0.32
Summary: Viewer for wind turbine simulation results built using threejs for python Dash
Home-page: UNKNOWN
Author: Ben Cannell <bean.can.design@gmail.com>
License: GPL-3.0
Platform: UNKNOWN
Classifier: Framework :: Dash
License-File: LICENSE
